killtracker/__init__.py
killtracker/admin.py
killtracker/app_settings.py
killtracker/apps.py
killtracker/constants.py
killtracker/exceptions.py
killtracker/forms.py
killtracker/managers.py
killtracker/providers.py
killtracker/tasks.py
killtracker/core/__init__.py
killtracker/core/discord_messages.py
killtracker/core/killmails.py
killtracker/management/commands/killtracker_load_eve.py
killtracker/migrations/0001_initial_new.py
killtracker/migrations/0001_squashed_all.py
killtracker/migrations/0002_fix_webhook_notes_field.py
killtracker/migrations/0002_tracker_require_attackers_weapon_groups_and_more.py
killtracker/migrations/0003_add_state_clauses.py
killtracker/migrations/0003_optimize_tracker_form.py
killtracker/migrations/0004_django4_update.py
killtracker/migrations/0005_add_final_blow_clause_and_more.py
killtracker/migrations/0006_evetypeplus.py
killtracker/migrations/0007_restructure_killsmails.py
killtracker/migrations/0008_copy_data_to_new_structure.py
killtracker/migrations/0009_remove_old_models.py
killtracker/migrations/__init__.py
killtracker/models/__init__.py
killtracker/models/killmails.py
killtracker/models/trackers.py
killtracker/models/webhooks.py
killtracker/static/killtracker/killtracker_logo.png
killtracker/static/killtracker/zkb_icon.png
killtracker/templates/admin/killtracker/tracker/killmail_test.html
killtracker/tests/__init__.py
killtracker/tests/test_admin.py
killtracker/tests/test_admin_2.py
killtracker/tests/test_exceptions.py
killtracker/tests/test_integration.py
killtracker/tests/test_tasks.py
killtracker/tests/core/__init__.py
killtracker/tests/core/test_discord_messages_1.py
killtracker/tests/core/test_discord_messages_2.py
killtracker/tests/core/test_killmails.py
killtracker/tests/models/__init__.py
killtracker/tests/models/test_killmails.py
killtracker/tests/models/test_trackers_1.py
killtracker/tests/models/test_trackers_2.py
killtracker/tests/models/test_webhook.py
killtracker/tests/testdata/__init__.py
aa_killtracker_pomver-0.14.0.dist-info/LICENSE
aa_killtracker_pomver-0.14.0.dist-info/WHEEL
aa_killtracker_pomver-0.14.0.dist-info/METADATA
aa_killtracker_pomver-0.14.0.dist-info/RECORD
