Metadata-Version: 2.1
Name: aa-killtracker-pomVer
Version: 0.14.0
Summary: "An app for running killmail trackers with Alliance Auth and Discord.
Author-email: Erik Kalkoken <kalkoken87@gmail.com>
Requires-Python: >=3.8
Classifier: Environment :: Web Environment
Classifier: Framework :: Django
Classifier: Framework :: Django :: 4.0
Classifier: Framework :: Django :: 4.2
Classifier: Intended Audience :: End Users/Desktop
Classifier: License :: OSI Approved :: MIT License
Classifier: Operating System :: OS Independent
Classifier: Programming Language :: Python
Classifier: Programming Language :: Python :: 3.8
Classifier: Programming Language :: Python :: 3.9
Classifier: Programming Language :: Python :: 3.10
Classifier: Programming Language :: Python :: 3.11
Classifier: Topic :: Internet :: WWW/HTTP
Classifier: Topic :: Internet :: WWW/HTTP :: Dynamic Content
Requires-Dist: allianceauth-app-utils>=1.19.0
Requires-Dist: allianceauth>=3
Requires-Dist: dacite
Requires-Dist: dhooks-lite>=1.0
Requires-Dist: django-eveuniverse>=1.3
Requires-Dist: redis-simple-mq>=0.5
Project-URL: Home, https://gitlab.com/ErikKalkoken/aa-killtracker
